peregrine/__init__.py
peregrine/ai_client.py
peregrine/cli.py
peregrine/main.py
peregrine/utils.py
peregrine_ai-0.2.1.dist-info/METADATA
peregrine_ai-0.2.1.dist-info/WHEEL
peregrine_ai-0.2.1.dist-info/entry_points.txt
peregrine_ai-0.2.1.dist-info/top_level.txt
peregrine_ai-0.2.1.dist-info/RECORD
