Metadata-Version: 2.1
Name: peregrine-ai
Version: 0.2.1
Summary: "Natural language AI helper for command line tools. "
Home-page: UNKNOWN
Author: UNKNOWN
Author-email: UNKNOWN
License: UNKNOWN
Platform: UNKNOWN
